xerberus/__init__.py
xerberus/client.py
xerberus/config.py
xerberus/queries/chains.graphql
xerberus/queries/metrics.graphql
xerberus/queries/tokens.graphql
xerberus/queries/tokens_by_similar_address.graphql
xerberus/queries/tokens_by_similar_symbol.graphql
xerberus_metrics_sdk-0.1.3.dist-info/licenses/LICENSE
xerberus_metrics_sdk-0.1.3.dist-info/METADATA
xerberus_metrics_sdk-0.1.3.dist-info/WHEEL
xerberus_metrics_sdk-0.1.3.dist-info/top_level.txt
xerberus_metrics_sdk-0.1.3.dist-info/RECORD
