Metadata-Version: 2.4
Name: xerberus-metrics-sdk
Version: 0.1.3
Summary: SDK to access Xerberus GraphQL metrics API
Author-email: Xerberus- Tomas Barrios <tb@xerberus.io>
License: MIT
License-File: LICENSE
Requires-Dist: requests>=2.31.0
Requires-Dist: python-dotenv>=1.0.1
Dynamic: license-file
